voladice/__init__.py
voladice/filters.py
voladice-0.2.0.dist-info/LICENSE
voladice-0.2.0.dist-info/METADATA
voladice-0.2.0.dist-info/WHEEL
voladice-0.2.0.dist-info/top_level.txt
voladice-0.2.0.dist-info/RECORD
