Metadata-Version: 2.1
Name: voladice
Version: 0.2.0
Summary: Dice rolling and result manipulation
Author-email: Volatus <veritasvolatus@gmail.com>
License: MIT License        
Project-URL: Source Code, https://github.com/volatusveritas/voladice
Classifier: Programming Language :: Python :: 3
Classifier: License :: OSI Approved :: MIT License
Classifier: Operating System :: OS Independent
Requires-Python: >=3.10
License-File: LICENSE
